myip/__init__.py
myip/main.py
myip_localip-0.0.7.dist-info/LICENSE
myip_localip-0.0.7.dist-info/METADATA
myip_localip-0.0.7.dist-info/WHEEL
myip_localip-0.0.7.dist-info/entry_points.txt
myip_localip-0.0.7.dist-info/top_level.txt
myip_localip-0.0.7.dist-info/RECORD
